geomad/__init__.py
geomad/_version.py
geomad/pcm.cp310-win32.pyd
geomad/pcm.pyx
geomad/utils.py
geomad-1.0.0.dist-info/licenses/LICENSE
geomad-1.0.0.dist-info/METADATA
geomad-1.0.0.dist-info/WHEEL
geomad-1.0.0.dist-info/top_level.txt
geomad-1.0.0.dist-info/RECORD
