Metadata-Version: 2.4
Name: geomad
Version: 1.0.0
Summary: Geomedian and Median Absolute Deviation implementation
Author: Geoscience Australia
License-Expression: Apache-2.0
Project-URL: Homepage, https://github.com/GeoscienceAustralia/geomad
Project-URL: Source, https://github.com/GeoscienceAustralia/geomad
Project-URL: Issues, https://github.com/GeoscienceAustralia/geomad/issues
Classifier: Development Status :: 4 - Beta
Classifier: Intended Audience :: Developers
Classifier: Intended Audience :: Science/Research
Classifier: Natural Language :: English
Classifier: Operating System :: MacOS :: MacOS X
Classifier: Operating System :: POSIX
Classifier: Operating System :: POSIX :: BSD
Classifier: Operating System :: POSIX :: Linux
Classifier: Operating System :: Microsoft :: Windows
Classifier: Programming Language :: Python
Classifier: Programming Language :: Python :: 3
Classifier: Programming Language :: Python :: 3.10
Classifier: Programming Language :: Python :: 3.11
Classifier: Programming Language :: Python :: 3.12
Classifier: Programming Language :: Python :: 3.13
Classifier: Topic :: Scientific/Engineering :: GIS
Classifier: Topic :: Scientific/Engineering :: Information Analysis
Requires-Python: >=3.10
License-File: LICENSE
Requires-Dist: numpy
Provides-Extra: test
Requires-Dist: pytest; extra == "test"
Requires-Dist: joblib; extra == "test"
Dynamic: license-file
